cellbell/__init__.py
cellbell/bell.wav
cellbell/cellbell.py
cellbell-0.0.3.dist-info/DESCRIPTION.rst
cellbell-0.0.3.dist-info/METADATA
cellbell-0.0.3.dist-info/RECORD
cellbell-0.0.3.dist-info/WHEEL
cellbell-0.0.3.dist-info/metadata.json
cellbell-0.0.3.dist-info/top_level.txt
