Metadata-Version: 2.0
Name: cellbell
Version: 0.0.3
Summary: Bell magic for jupyter notebook
Home-page: https://github.com/lepisma/cellbell
Author: Abhinav Tushar
Author-email: abhinav.tushar.vs@gmail.com
License: MIT
Keywords: ipython,magic,bell,notification
Platform: UNKNOWN
Classifier: Programming Language :: Python :: 2
Classifier: Programming Language :: Python :: 3
Requires-Dist: pyglet
